lazyConfig/__init__.py
lazyConfig/config.py
lazyConfig/factory.py
lazyConfig/lazyData.py
lazyConfig-0.5.dist-info/LICENCE
lazyConfig-0.5.dist-info/METADATA
lazyConfig-0.5.dist-info/WHEEL
lazyConfig-0.5.dist-info/top_level.txt
lazyConfig-0.5.dist-info/RECORD
