Metadata-Version: 2.1
Name: lazyConfig
Version: 0.5
Summary: lazily loading and overriding configuration for the lazy coder
Home-page: https://github.com/FelixBenning/lazyConfig
Author: Felix Benning
Author-email: felix.benning@gmail.com
License: UNKNOWN
Platform: UNKNOWN
Classifier: Programming Language :: Python :: 3
Classifier: License :: OSI Approved :: Mozilla Public License 2.0 (MPL 2.0)
Classifier: Development Status :: 4 - Beta
Requires-Python: >=3.8
Requires-Dist: pyYAML (>=5.3.1<6)
Requires-Dist: toml (>=0.10.1<1)
Requires-Dist: deprecation (>=2.1<3)
